pydepm/__init__.py
pydepm/__main__.py
pydepm/cli.py
pydepm/config.py
pydepm/installer.py
pydepm/pydepx.py
pydepm/utils.py
pydepm/validation.py
pydepm-1.1.2.dist-info/licenses/LICENSE
pydepm-1.1.2.dist-info/METADATA
pydepm-1.1.2.dist-info/WHEEL
pydepm-1.1.2.dist-info/entry_points.txt
pydepm-1.1.2.dist-info/top_level.txt
pydepm-1.1.2.dist-info/RECORD
