Metadata-Version: 2.4
Name: pydepm
Version: 1.1.2
Summary: PyDepM — Python Dependency Manager
Author: ZtaDev
License-Expression: MIT
Project-URL: Homepage, https://github.com/ZtaMDev/PyDepM
Project-URL: Repository, https://github.com/ZtaMDev/PyDepM.git
Project-URL: Issues, https://github.com/ZtaMDev/PyDepM/issues
Requires-Python: >=3.9
License-File: LICENSE
Requires-Dist: typer>=0.12.3
Requires-Dist: rich>=13.7.0
Requires-Dist: packaging>=24.0
Requires-Dist: build>=1.2.1
Requires-Dist: twine>=5.0.0
Requires-Dist: pip-audit>=2.9.0
Requires-Dist: pyinstaller>=6.0.0
Requires-Dist: pytest>=8.3.4
Requires-Dist: toml>=0.10.2
Requires-Dist: pip-api>=0.0.34
Dynamic: license-file
